dockerensure/__init__.py
dockerensure/buildconfig.py
dockerensure/filepolicy.py
dockerensure/hasher.py
dockerensure/image.py
dockerensure/registry.py
dockerensure/utils.py
dockerensure-0.0.3.dist-info/WHEEL
dockerensure-0.0.3.dist-info/METADATA
dockerensure-0.0.3.dist-info/RECORD
