Metadata-Version: 2.1
Name: dockerensure
Version: 0.0.3
Summary: Ensure that Docker images are ready for use
Home-page: https://github.com/ubuntom/dockerensure
License: MIT
Author: ubuntom
Requires-Python: >=3.8,<4.0
Classifier: License :: OSI Approved :: MIT License
Classifier: Operating System :: OS Independent
Classifier: Programming Language :: Python :: 3
Classifier: Programming Language :: Python :: 3.10
Classifier: Programming Language :: Python :: 3.8
Classifier: Programming Language :: Python :: 3.9
